jfd/__init__.py
jfd/diff.py
jfd/operator.py
jfd-0.0.0.dist-info/METADATA
jfd-0.0.0.dist-info/WHEEL
jfd-0.0.0.dist-info/top_level.txt
jfd-0.0.0.dist-info/RECORD
